LICENSE
README.md
setup.py
src/yuptools/__init__.py
src/yuptools.egg-info/PKG-INFO
src/yuptools.egg-info/SOURCES.txt
src/yuptools.egg-info/dependency_links.txt
src/yuptools.egg-info/requires.txt
src/yuptools.egg-info/top_level.txt
src/yuptools/attacks/__init__.py
src/yuptools/attacks/fgsm.py
src/yuptools/attacks/ifgsm.py
src/yuptools/datasets/__init__.py
src/yuptools/datasets/base.py
src/yuptools/datasets/image_classification.py
src/yuptools/datasets/class_labels/__init__.py
src/yuptools/datasets/class_labels/cifar10.py
src/yuptools/datasets/class_labels/cifar100.py
src/yuptools/datasets/class_labels/fashionmnist.py
src/yuptools/datasets/class_labels/imagenet.py
src/yuptools/datasets/class_labels/mnist.py
src/yuptools/models/__init__.py
src/yuptools/models/xray.py
src/yuptools/models/classification/__init__.py
src/yuptools/models/classification/base.py
src/yuptools/models/classification/config.py
src/yuptools/models/classification/models.py
src/yuptools/models/classification/warnings.py
src/yuptools/models/classification/weights.py
src/yuptools/models/classification/nets/__init__.py
src/yuptools/models/classification/nets/deit.py
src/yuptools/models/classification/nets/mixer.py
src/yuptools/models/classification/nets/poolformer.py
src/yuptools/models/classification/nets/pvt.py
src/yuptools/models/replace/__init__.py
src/yuptools/models/replace/activation.py
src/yuptools/models/replace/base.py
src/yuptools/models/replace/common.py
src/yuptools/models/replace/config.py
src/yuptools/models/replace/normalization.py
src/yuptools/models/test/__init__.py
src/yuptools/models/test/accuracy.py
src/yuptools/models/test/calibration.py
src/yuptools/models/test/linearity.py
src/yuptools/plotlib/__init__.py
src/yuptools/plotlib/bar.py
src/yuptools/plotlib/base.py
src/yuptools/plotlib/common.py
src/yuptools/tools/__init__.py
src/yuptools/tools/attrtools.py
src/yuptools/tools/dictools.py
src/yuptools/tools/imgtools.py
src/yuptools/tools/linalgtools.py
src/yuptools/tools/listools.py
src/yuptools/tools/pathtools.py
src/yuptools/tools/randtools.py
src/yuptools/train/__init__.py
src/yuptools/train/base.py
src/yuptools/train/criterion.py
