Metadata-Version: 2.1
Name: yuptools
Version: 0.1.9
Home-page: https://github.com/yupeeee/YupTools
Author: Juyeop Kim
Author-email: juyeopkim@yonsei.ac.kr
License: MIT
License-File: LICENSE
